setup.py
pyripple/__init__.py
pyripple.egg-info/PKG-INFO
pyripple.egg-info/SOURCES.txt
pyripple.egg-info/dependency_links.txt
pyripple.egg-info/not-zip-safe
pyripple.egg-info/pbr.json
pyripple.egg-info/requires.txt
pyripple.egg-info/top_level.txt
pyripple/feed/__init__.py
pyripple/feed/syncfeed.py
pyripple/protocol/__init__.py
pyripple/protocol/ledger.py
pyripple/protocol/orderbook.py
pyripple/websocket/__init__.py
pyripple/websocket/client.py