Metadata-Version: 1.0
Name: pyripple
Version: 0.0.1
Summary: Python package for data analysis of the Ripple peer-to-peer network
Home-page: http://github.com/gip/pyripple
Author: Gilles Pirio
Author-email: gilles.xrp@gmail.com
License: Apache License 2.0
Platform: UNKNOWN
